colorit/__init__.py
colorit/__main__.py
colorit/colorit.py
color_it-2.1.3.dist-info/LICENSE
color_it-2.1.3.dist-info/METADATA
color_it-2.1.3.dist-info/WHEEL
color_it-2.1.3.dist-info/top_level.txt
color_it-2.1.3.dist-info/RECORD
