Metadata-Version: 2.1
Name: color-it
Version: 2.1.3
Summary: A cross-platform lightweight package for printing colors in the terminal.
Home-page: https://github.com/CodeForeverAndEver/colorit
Author: SuperMaZingCoder
Author-email: supermazingcoder@gmail.com
License: UNKNOWN
Platform: UNKNOWN
Classifier: Programming Language :: Python :: 3
Classifier: License :: OSI Approved :: MIT License
Classifier: Operating System :: OS Independent
Requires-Python: >=3.6
